apriltag/__init__.py
apriltag/apriltag.cpython-314-x86_64-linux-musl.so
apriltag_pywrapper-3.4.5.data/data/include/apriltag/apriltag.h
apriltag_pywrapper-3.4.5.data/data/include/apriltag/apriltag_math.h
apriltag_pywrapper-3.4.5.data/data/include/apriltag/apriltag_pose.h
apriltag_pywrapper-3.4.5.data/data/include/apriltag/tag16h5.h
apriltag_pywrapper-3.4.5.data/data/include/apriltag/tag25h9.h
apriltag_pywrapper-3.4.5.data/data/include/apriltag/tag36h10.h
apriltag_pywrapper-3.4.5.data/data/include/apriltag/tag36h11.h
apriltag_pywrapper-3.4.5.data/data/include/apriltag/tagCircle21h7.h
apriltag_pywrapper-3.4.5.data/data/include/apriltag/tagCircle49h12.h
apriltag_pywrapper-3.4.5.data/data/include/apriltag/tagCustom48h12.h
apriltag_pywrapper-3.4.5.data/data/include/apriltag/tagStandard41h12.h
apriltag_pywrapper-3.4.5.data/data/include/apriltag/tagStandard52h13.h
apriltag_pywrapper-3.4.5.data/data/include/apriltag/common/debug_print.h
apriltag_pywrapper-3.4.5.data/data/include/apriltag/common/doubles.h
apriltag_pywrapper-3.4.5.data/data/include/apriltag/common/doubles_floats_impl.h
apriltag_pywrapper-3.4.5.data/data/include/apriltag/common/floats.h
apriltag_pywrapper-3.4.5.data/data/include/apriltag/common/g2d.h
apriltag_pywrapper-3.4.5.data/data/include/apriltag/common/getopt.h
apriltag_pywrapper-3.4.5.data/data/include/apriltag/common/homography.h
apriltag_pywrapper-3.4.5.data/data/include/apriltag/common/image_types.h
apriltag_pywrapper-3.4.5.data/data/include/apriltag/common/image_u8.h
apriltag_pywrapper-3.4.5.data/data/include/apriltag/common/image_u8_parallel.h
apriltag_pywrapper-3.4.5.data/data/include/apriltag/common/image_u8x3.h
apriltag_pywrapper-3.4.5.data/data/include/apriltag/common/image_u8x4.h
apriltag_pywrapper-3.4.5.data/data/include/apriltag/common/matd.h
apriltag_pywrapper-3.4.5.data/data/include/apriltag/common/math_util.h
apriltag_pywrapper-3.4.5.data/data/include/apriltag/common/pam.h
apriltag_pywrapper-3.4.5.dist-info/METADATA
apriltag_pywrapper-3.4.5.dist-info/WHEEL
apriltag_pywrapper-3.4.5.dist-info/top_level.txt
apriltag_pywrapper-3.4.5.dist-info/RECORD
