Metadata-Version: 2.4
Name: apriltag-pywrapper
Version: 3.4.5
Summary: Lightweight pip-installable wrapper for AprilTag with full tag family support
Home-page: https://github.com/pcarnah/apriltag-pywrapper
Author: Patrick Carnahan
Classifier: Programming Language :: Python :: 3
Classifier: Operating System :: OS Independent
Requires-Python: >=3.7
Requires-Dist: numpy
Dynamic: author
Dynamic: classifier
Dynamic: home-page
Dynamic: requires-dist
Dynamic: requires-python
Dynamic: summary
